serve_shiny/__init__.py
serve_shiny/admin.py
serve_shiny/apps.py
serve_shiny/models.py
serve_shiny/shiny_cleanup.py
serve_shiny/signals.py
serve_shiny/tests.py
serve_shiny/urls.py
serve_shiny/utils.py
serve_shiny/views.py
serve_shiny/migrations/__init__.py
serve_shiny/templates/serve_shiny/shiny_wrapper.html
django_serve_shiny-0.1.dist-info/LICENSE
django_serve_shiny-0.1.dist-info/METADATA
django_serve_shiny-0.1.dist-info/WHEEL
django_serve_shiny-0.1.dist-info/top_level.txt
django_serve_shiny-0.1.dist-info/RECORD
